{
    "name": "collageplus",
    "title": "CollagePlus Gallery",
    "description": "An image grid gallery plugin for jQuery.",
    "keywords": [
        "grid",
        "gallery",
        "photography",
        "album",
        "masonry"
    ],
    "version": "0.3.3",
    "author": {
        "name": "Ed Lea",
        "url": "http://edlea.com"
    },
    "maintainers": [
        {
            "name": "Ed Lea",
            "email": "edleadesign@gmail.com",
            "url": "http://edlea.com"
        }
    ],
    "licenses": [
        {
            "type": "MIT",
            "url": "http://www.opensource.org/licenses/mit-license.php"
        }
    ],
    "bugs": "https://github.com/ed-lea/jquery-collagePlus/issues",
    "homepage": "http://collageplus.edlea.com/",
    "docs": "http://collageplus.edlea.com/",
    "download": "https://github.com/ed-lea/jquery-collagePlus/zipball/master",
    "dependencies": {
        "jquery": ">=1.7"
    }
}